test/__init__.py
test/test_yafg.py
yafg/__init__.py
yafg/yafg.py
yafg-0.3.dist-info/LICENSE
yafg-0.3.dist-info/METADATA
yafg-0.3.dist-info/WHEEL
yafg-0.3.dist-info/entry_points.txt
yafg-0.3.dist-info/top_level.txt
yafg-0.3.dist-info/RECORD
