Metadata-Version: 2.1
Name: yafg
Version: 0.3
Summary: Figure and figcaption generator markdown extension
Home-page: https://git.sr.ht/~ferruck/yafg
Author: Philipp Trommler
Author-email: yafg@philipp-trommler.me
Maintainer: Philipp Trommler
Maintainer-email: yafg@philipp-trommler.me
License: GPLv3+
Keywords: markdown image figure caption html a11y
Platform: UNKNOWN
Classifier: Development Status :: 4 - Beta
Classifier: Environment :: Plugins
Classifier: Intended Audience :: Developers
Classifier: License :: OSI Approved :: GNU General Public License v3 or later (GPLv3+)
Classifier: Operating System :: OS Independent
Classifier: Programming Language :: Python
Classifier: Programming Language :: Python :: 2
Classifier: Programming Language :: Python :: 2.7
Classifier: Programming Language :: Python :: 3
Classifier: Programming Language :: Python :: 3.6
Classifier: Programming Language :: Python :: Implementation :: CPython
Classifier: Topic :: Documentation
Classifier: Topic :: Text Processing :: Markup
Requires-Python: >=2.7.15, !=3.0.*, !=3.1.*, !=3.2.*, !=3.3.*, !=3.4.*, !=3.5.*, <4
Requires-Dist: Markdown (>=3.1.1)
